Metadata-Version: 2.1
Name: stats265
Version: 0.5
Summary: Some Stats distributions
Home-page: https://github.com/TanyaradzwaGozhora/stats265
Author: Tanyaradzwa Gozhora
Author-email: tanyaradzwagozhora@gmail.com
License: UNKNOWN
Project-URL: Stats265-distributions, https://github.com/TanyaradzwaGozhora/stats265
Platform: UNKNOWN
Classifier: Programming Language :: Python :: 3
Classifier: License :: OSI Approved :: MIT License
Classifier: Operating System :: OS Independent
Requires-Python: >=3.6
License-File: LICENSE
